Metadata-Version: 2.1
Name: robotter-hummingbot
Version: 20241016
Summary: Hummingbot
Home-page: https://github.com/robotter-ai/hummingbot
Author: robotter.ai
Author-email: me@hoangla.xyz
License: Apache 2.0
License-File: LICENSE
Requires-Dist: bidict
Requires-Dist: aioconsole
Requires-Dist: aiohttp
Requires-Dist: aioprocessing
Requires-Dist: asyncssh
Requires-Dist: appdirs
Requires-Dist: appnope
Requires-Dist: async-timeout
Requires-Dist: base58
Requires-Dist: cachetools
Requires-Dist: certifi
Requires-Dist: coincurve
Requires-Dist: cryptography
Requires-Dist: cython ==3.0.0
Requires-Dist: cytoolz
Requires-Dist: commlib-py
Requires-Dist: docker
Requires-Dist: diff-cover
Requires-Dist: ecdsa
Requires-Dist: eip712-structs
Requires-Dist: eth-abi
Requires-Dist: eth-account
Requires-Dist: eth-bloom
Requires-Dist: eth-keyfile
Requires-Dist: eth-typing
Requires-Dist: eth-utils
Requires-Dist: flake8
Requires-Dist: grpcio
Requires-Dist: hexbytes
Requires-Dist: importlib-metadata
Requires-Dist: injective-py
Requires-Dist: mypy-extensions
Requires-Dist: msgpack
Requires-Dist: nose
Requires-Dist: nose-exclude
Requires-Dist: numpy ==1.26.4
Requires-Dist: pandas
Requires-Dist: pip
Requires-Dist: pre-commit
Requires-Dist: prompt-toolkit
Requires-Dist: protobuf
Requires-Dist: psutil
Requires-Dist: pydantic
Requires-Dist: pyjwt
Requires-Dist: pyperclip
Requires-Dist: python-dateutil
Requires-Dist: python-telegram-bot ==12.8
Requires-Dist: pyOpenSSL
Requires-Dist: requests
Requires-Dist: rsa
Requires-Dist: ruamel-yaml
Requires-Dist: scipy
Requires-Dist: signalr-client-aio
Requires-Dist: simplejson
Requires-Dist: six
Requires-Dist: sqlalchemy
Requires-Dist: tabulate
Requires-Dist: tzlocal
Requires-Dist: ujson
Requires-Dist: web3
Requires-Dist: websockets
Requires-Dist: yarl
Requires-Dist: pandas-ta ==0.3.14b
Requires-Dist: xrpl-py ==3.0.0
